COPYING
MANIFEST.in
README.md
pyproject.toml
django_eventstream/__init__.py
django_eventstream/admin.py
django_eventstream/apps.py
django_eventstream/channelmanager.py
django_eventstream/event.py
django_eventstream/eventrequest.py
django_eventstream/eventresponse.py
django_eventstream/eventstream.py
django_eventstream/models.py
django_eventstream/storage.py
django_eventstream/tests.py
django_eventstream/urls.py
django_eventstream/utils.py
django_eventstream/views.py
django_eventstream/viewsets.py
django_eventstream.egg-info/PKG-INFO
django_eventstream.egg-info/SOURCES.txt
django_eventstream.egg-info/dependency_links.txt
django_eventstream.egg-info/not-zip-safe
django_eventstream.egg-info/requires.txt
django_eventstream.egg-info/top_level.txt
django_eventstream/management/__init__.py
django_eventstream/management/commands/__init__.py
django_eventstream/management/commands/runserver_ngrok.py
django_eventstream/migrations/0001_initial.py
django_eventstream/migrations/__init__.py
django_eventstream/renderers/__init__.py
django_eventstream/renderers/browsableapieventstreamrenderer.py
django_eventstream/renderers/sserenderer.py
django_eventstream/static/django_eventstream/ReconnectingEventSource.min.js.map
django_eventstream/static/django_eventstream/eventsource.min.js
django_eventstream/static/django_eventstream/json2.js
django_eventstream/static/django_eventstream/reconnecting-eventsource.js
django_eventstream/static/django_eventstream/css/browsable-api-eventstream.css
django_eventstream/static/django_eventstream/js/browsable-api-eventstream.js
django_eventstream/templates/django_eventstream/browsable-api-eventstream.html
tests/test_storage.py
tests/test_stream.py