Metadata-Version: 2.4
Name: django-eventstream
Version: 5.3.3
Summary: Server-Sent Events for Django
Author-email: Justin Karneges <justin@fanout.io>
License: MIT
Project-URL: homepage, https://github.com/fanout/django-eventstream
Classifier: Development Status :: 4 - Beta
Classifier: Topic :: Utilities
Classifier: License :: OSI Approved :: MIT License
Classifier: Programming Language :: Python
Classifier: Programming Language :: Python :: 3
Classifier: Framework :: Django
Requires-Python: >=3.10
License-File: COPYING
Requires-Dist: Django>=5
Requires-Dist: PyJWT<3,>=1.5
Requires-Dist: gripcontrol<5,>=4.0
Requires-Dist: django_grip<4,>=3.0
Requires-Dist: six<2,>=1.10
Provides-Extra: drf
Requires-Dist: djangorestframework>=3.16.1; extra == "drf"
Dynamic: license-file
